{
    "adId": 587654,
    "state": "Expired",
    "title": "Plasterer - \u00a318.00 per hour - Stevenston",
    "reference": "NACTSP2901",
    "summary": "Recruitment Direct UK Ltd is looking for a time served Plasterer for their Local Authority Client based in Stevenston, North Ayrshire.",
    "bulletPoints": [
        "Valid CSCS card",
        "\u00a318 per hour",
        "Immediate Start"
    ],
    "description": "<strong>Recruitment Direct UK Ltd</strong> is looking for a time served<strong> Plasterer</strong> for their Local Authority Client based in <strong>Stevenston, North Ayrshire.</strong><br><br>Role will include dampness work/plastering work, also include hacking off plaster, dehumidifiers vents, membrane and thermal boarding and chemical injection of walls. Wash down and stain painting may also be included.<br><br> <ul> <li><strong> Valid CSCS card</strong></li> <li><strong> Time served plasterer</strong></li> <li><strong>Immediate Start</strong></li> <li><strong>&pound;18 per hour</strong></li> </ul> Working throughout North Ayrshire.&nbsp; Transport provided for working hours. Start and finish in the Stevenston yard.<br><br>INDCON",
    "job": {
        "jobId": 1148936,
        "jobTitle": "Plasterer",
        "location": {
            "locationId": 8357,
            "name": "Scotland-North Ayrshire"
        },
        "company": {
            "companyId": 1585477,
            "name": "North Ayrshire Council - Head office",
            "status": {
                "statusId": 522,
                "name": "Active client",
                "active": true,
                "default": true
            },
            "owner": {
                "userId": 1358,
                "firstName": "Nicola",
                "lastName": "Barbour",
                "position": "Construction Manager",
                "jobTitle": "Construction Manager",
                "email": "nicola@rd1.co.uk",
                "phone": "01324 613198",
                "mobile": "07590882626",
                "links": {
                    "self": "https://eu3api.jobadder.com/v2/users/1358"
                }
            },
            "links": {
                "self": "https://eu3api.jobadder.com/v2/companies/1585477",
                "mainContact": "https://eu3api.jobadder.com/v2/contacts/10412937"
            }
        },
        "contact": {
            "contactId": 7112971,
            "firstName": "Holly",
            "lastName": "Crawford",
            "position": "Business Support Supervisor",
            "unsubscribed": false,
            "email": "hollycrawford@north-ayrshire.gov.uk",
            "phone": "01294 445226",
            "status": {
                "statusId": 234,
                "name": "Active contact",
                "active": true,
                "default": true
            },
            "owner": {
                "userId": 1358,
                "firstName": "Nicola",
                "lastName": "Barbour",
                "position": "Construction Manager",
                "jobTitle": "Construction Manager",
                "email": "nicola@rd1.co.uk",
                "phone": "01324 613198",
                "mobile": "07590882626"
            },
            "links": {
                "self": "https://eu3api.jobadder.com/v2/contacts/7112971",
                "photo": "https://eu3api.jobadder.com/v2/contacts/7112971/photo",
                "company": "https://eu3api.jobadder.com/v2/companies/1585477"
            }
        },
        "status": {
            "statusId": 803,
            "name": "Open",
            "active": true,
            "default": true
        },
        "source": "Existing client",
        "owner": {
            "userId": 1358,
            "firstName": "Nicola",
            "lastName": "Barbour",
            "position": "Construction Manager",
            "jobTitle": "Construction Manager",
            "email": "nicola@rd1.co.uk",
            "phone": "01324 613198",
            "mobile": "07590882626"
        },
        "links": {
            "self": "https://eu3api.jobadder.com/v2/jobs/1148936"
        }
    },
    "company": {
        "companyId": 1585477,
        "name": "North Ayrshire Council - Head office",
        "status": {
            "statusId": 522,
            "name": "Active client",
            "active": true,
            "default": true
        },
        "owner": {
            "userId": 1358,
            "firstName": "Nicola",
            "lastName": "Barbour",
            "position": "Construction Manager",
            "jobTitle": "Construction Manager",
            "email": "nicola@rd1.co.uk",
            "phone": "01324 613198",
            "mobile": "07590882626",
            "links": {
                "self": "https://eu3api.jobadder.com/v2/users/1358"
            }
        },
        "links": {
            "self": "https://eu3api.jobadder.com/v2/companies/1585477",
            "mainContact": "https://eu3api.jobadder.com/v2/contacts/10412937"
        }
    },
    "contact": {
        "contactId": 7112971,
        "firstName": "Holly",
        "lastName": "Crawford",
        "position": "Business Support Supervisor",
        "unsubscribed": false,
        "email": "hollycrawford@north-ayrshire.gov.uk",
        "phone": "01294 445226",
        "status": {
            "statusId": 234,
            "name": "Active contact",
            "active": true,
            "default": true
        },
        "owner": {
            "userId": 1358,
            "firstName": "Nicola",
            "lastName": "Barbour",
            "position": "Construction Manager",
            "jobTitle": "Construction Manager",
            "email": "nicola@rd1.co.uk",
            "phone": "01324 613198",
            "mobile": "07590882626"
        },
        "links": {
            "self": "https://eu3api.jobadder.com/v2/contacts/7112971",
            "photo": "https://eu3api.jobadder.com/v2/contacts/7112971/photo",
            "company": "https://eu3api.jobadder.com/v2/companies/1585477"
        }
    },
    "jobBoards": [
        {
            "boardId": 369,
            "name": "Indeed",
            "reference": "llhmugg6aaautatxi2zle5pix4"
        },
        {
            "boardId": 460,
            "name": "Recruitment Direct - CareersPage",
            "reference": "3whqhdcnf25evewe3ff3yd7q3m"
        }
    ],
    "otherApplyUrls": [
        {
            "name": "LinkedIn",
            "url": "https://adr.to/mbfgmai"
        },
        {
            "name": "Twitter",
            "url": "https://adr.to/mffgmai"
        },
        {
            "name": "Facebook",
            "url": "https://adr.to/mjfgmai"
        },
        {
            "name": "Indeed",
            "url": "https://adr.to/mnfgmai"
        }
    ],
    "owner": {
        "userId": 1358,
        "firstName": "Nicola",
        "lastName": "Barbour",
        "position": "Construction Manager",
        "jobTitle": "Construction Manager",
        "email": "nicola@rd1.co.uk",
        "phone": "01324 613198",
        "mobile": "07590882626",
        "links": {
            "self": "https://eu3api.jobadder.com/v2/users/1358"
        }
    },
    "createdBy": {
        "userId": 1358,
        "firstName": "Nicola",
        "lastName": "Barbour",
        "position": "Construction Manager",
        "jobTitle": "Construction Manager",
        "email": "nicola@rd1.co.uk",
        "phone": "01324 613198",
        "mobile": "07590882626"
    },
    "createdAt": "2025-01-29T14:23:19Z",
    "postAt": "2025-01-29T14:23:25Z",
    "expireAt": "2025-01-31T10:59:56Z",
    "links": {
        "self": "https://eu3api.jobadder.com/v2/jobads/587654",
        "applications": "https://eu3api.jobadder.com/v2/jobads/587654/applications"
    }
}